payloadforge/__init__.py
payloadforge/cli.py
payloadforge/disclaimer.py
payloadforge/logger.py
payloadforge/encoders/__init__.py
payloadforge/encoders/base64_enc.py
payloadforge/encoders/html.py
payloadforge/encoders/unicode.py
payloadforge/encoders/url.py
payloadforge/generators/__init__.py
payloadforge/generators/cmdi.py
payloadforge/generators/sqli.py
payloadforge/generators/ssti.py
payloadforge/generators/xss.py
payloadforge/utils/__init__.py
payloadforge/utils/obfuscation.py
payloadforge-1.0.2.dist-info/licenses/LICENSE
payloadforge-1.0.2.dist-info/METADATA
payloadforge-1.0.2.dist-info/WHEEL
payloadforge-1.0.2.dist-info/entry_points.txt
payloadforge-1.0.2.dist-info/top_level.txt
payloadforge-1.0.2.dist-info/RECORD
