Metadata-Version: 2.4
Name: payloadforge
Version: 1.0.2
Summary: A toolkit for generating safe cybersecurity payloads for ethical testing and research
Author-email: Bala Kavi <balakavi64@gmail.com>
License: MIT
Project-URL: Homepage, https://github.com/mr-bala-kavi/payloadforge
Project-URL: Documentation, https://github.com/mr-bala-kavi/payloadforge#readme
Project-URL: Repository, https://github.com/mr-bala-kavi/payloadforge
Project-URL: Issues, https://github.com/mr-bala-kavi/payloadforge/issues
Keywords: cybersecurity,pentest,payload,xss,sqli,security-testing
Classifier: Development Status :: 4 - Beta
Classifier: Intended Audience :: Developers
Classifier: Intended Audience :: Information Technology
Classifier: License :: OSI Approved :: MIT License
Classifier: Operating System :: OS Independent
Classifier: Programming Language :: Python :: 3
Classifier: Programming Language :: Python :: 3.8
Classifier: Programming Language :: Python :: 3.9
Classifier: Programming Language :: Python :: 3.10
Classifier: Programming Language :: Python :: 3.11
Classifier: Programming Language :: Python :: 3.12
Classifier: Topic :: Security
Classifier: Topic :: Software Development :: Libraries :: Python Modules
Requires-Python: >=3.8
License-File: LICENSE
Requires-Dist: click>=8.0.0
Requires-Dist: colorama>=0.4.4
Requires-Dist: pyyaml>=6.0
Provides-Extra: dev
Requires-Dist: pytest>=7.0.0; extra == "dev"
Requires-Dist: pytest-cov>=4.0.0; extra == "dev"
Requires-Dist: black>=23.0.0; extra == "dev"
Requires-Dist: flake8>=6.0.0; extra == "dev"
Dynamic: license-file
